[
    {
        "label": "1",
        "page_number": 2,
        "bbox": [
            46,
            62,
            56,
            78
        ],
        "level": 46,
        "parts": [
            {
                "label": "(a)",
                "page_number": 2,
                "bbox": [
                    69,
                    208,
                    87,
                    223
                ],
                "level": 69,
                "parts": [],
                "content": [
                    {
                        "type": "text",
                        "text": "Find the probability that the student plays the guitar",
                        "bbox": [
                            92,
                            208,
                            344,
                            223
                        ],
                        "page_number": 2,
                        "is_pre": false,
                        "issues": [],
                        "is_pot_pre": false
                    },
                    {
                        "type": "mark_text",
                        "text": "[1]",
                        "bbox": [
                            508,
                            208,
                            528,
                            223
                        ],
                        "page_number": 2,
                        "is_pre": false,
                        "is_pot_pre": false
                    }
                ],
                "issues": []
            },
            {
                "label": "(b)",
                "page_number": 2,
                "bbox": [
                    70,
                    326,
                    87,
                    341
                ],
                "level": 70,
                "parts": [],
                "content": [
                    {
                        "type": "text",
                        "text": "Find the probability that the student is male given that the student plays the drums",
                        "bbox": [
                            93,
                            326,
                            486,
                            341
                        ],
                        "page_number": 2,
                        "is_pre": false,
                        "issues": [],
                        "is_pot_pre": false
                    },
                    {
                        "type": "mark_text",
                        "text": "[2]",
                        "bbox": [
                            508,
                            326,
                            528,
                            341
                        ],
                        "page_number": 2,
                        "is_pre": false,
                        "is_pot_pre": false
                    }
                ],
                "issues": []
            },
            {
                "label": "(c)",
                "page_number": 2,
                "bbox": [
                    70,
                    501,
                    87,
                    516
                ],
                "level": 70,
                "parts": [],
                "content": [
                    {
                        "type": "text",
                        "text": "Determine whether the events ‘the student plays the guitar’ and ‘the student is female’ are independent, justifying your answer",
                        "bbox": [
                            93,
                            501,
                            548,
                            529
                        ],
                        "page_number": 2,
                        "is_pre": false,
                        "issues": [],
                        "is_pot_pre": false
                    },
                    {
                        "type": "mark_text",
                        "text": "[2]",
                        "bbox": [
                            508,
                            513,
                            528,
                            529
                        ],
                        "page_number": 2,
                        "is_pre": false,
                        "is_pot_pre": false
                    }
                ],
                "issues": []
            }
        ],
        "content": [
            {
                "type": "text",
                "text": "Each of the 180 students at a college plays exactly one of the piano, the guitar and the drums. The numbers of male and female students who play the piano, the guitar and the drums are given in the following table",
                "bbox": [
                    70,
                    62,
                    548,
                    105
                ],
                "page_number": 2,
                "is_pre": false,
                "issues": [],
                "is_pot_pre": false
            },
            {
                "type": "table",
                "bbox": [
                    211,
                    112,
                    406,
                    169
                ],
                "page_number": 2,
                "is_pre": false,
                "table": {
                    "html": "<table><tr><td></td><td>Piano</td><td>Guitar</td><td>Drums</td></tr><tr><td>Male</td><td>25</td><td>44</td><td>11</td></tr><tr><td>Female</td><td>42</td><td>38</td><td>20</td></tr></table>"
                },
                "issues": [],
                "is_pot_pre": false
            },
            {
                "type": "text",
                "text": "A student at the college is chosen at random",
                "bbox": [
                    70,
                    182,
                    285,
                    197
                ],
                "page_number": 2,
                "is_pre": false,
                "issues": [],
                "is_pot_pre": false
            }
        ],
        "issues": [],
        "is_multi": false
    },
    {
        "label": "2",
        "page_number": 3,
        "bbox": [
            45,
            62,
            57,
            78
        ],
        "level": 45,
        "parts": [
            {
                "label": "(a)",
                "page_number": 3,
                "bbox": [
                    69,
                    88,
                    87,
                    104
                ],
                "level": 69,
                "parts": [],
                "content": [
                    {
                        "type": "text",
                        "text": "In how many different ways can a group of 6 be chosen if it must contain exactly 1 man?",
                        "bbox": [
                            93,
                            88,
                            547,
                            104
                        ],
                        "page_number": 3,
                        "is_pre": false,
                        "issues": [],
                        "is_pot_pre": false
                    },
                    {
                        "type": "mark_text",
                        "text": "[2]",
                        "bbox": [
                            508,
                            88,
                            528,
                            104
                        ],
                        "page_number": 3,
                        "is_pre": false,
                        "is_pot_pre": false
                    }
                ],
                "issues": []
            },
            {
                "label": "(b)",
                "page_number": 3,
                "bbox": [
                    69,
                    402,
                    88,
                    417
                ],
                "level": 69,
                "parts": [],
                "content": [
                    {
                        "type": "pre_text",
                        "text": "Two of the 11 women are sisters Jane and Kate",
                        "bbox": [
                            69,
                            374,
                            298,
                            390
                        ],
                        "page_number": 3,
                        "is_pre": true,
                        "issues": [],
                        "is_pot_pre": true
                    },
                    {
                        "type": "text",
                        "text": "In how many different ways can a group of 6 be chosen if Jane and Kate cannot both be in the group?",
                        "bbox": [
                            93,
                            402,
                            548,
                            430
                        ],
                        "page_number": 3,
                        "is_pre": false,
                        "issues": [],
                        "is_pot_pre": false
                    },
                    {
                        "type": "mark_text",
                        "text": "[3]",
                        "bbox": [
                            508,
                            414,
                            528,
                            430
                        ],
                        "page_number": 3,
                        "is_pre": false,
                        "is_pot_pre": false
                    }
                ],
                "issues": []
            }
        ],
        "content": [
            {
                "type": "text",
                "text": "A group of 6 people is to be chosen from 4 men and 11 women",
                "bbox": [
                    70,
                    62,
                    374,
                    78
                ],
                "page_number": 3,
                "is_pre": false,
                "issues": [],
                "is_pot_pre": false
            }
        ],
        "issues": [],
        "is_multi": false
    },
    {
        "label": "3",
        "page_number": 4,
        "bbox": [
            46,
            63,
            56,
            78
        ],
        "level": 46,
        "parts": [
            {
                "label": "(a)",
                "page_number": 4,
                "bbox": [
                    69,
                    102,
                    87,
                    118
                ],
                "level": 69,
                "parts": [],
                "content": [
                    {
                        "type": "text",
                        "text": "Show that the probability that exactly one of the marbles is yellow is \\(\\frac{5}{14}\\)",
                        "bbox": [
                            94,
                            101,
                            436,
                            118
                        ],
                        "page_number": 4,
                        "is_pre": false,
                        "issues": [],
                        "is_pot_pre": false
                    },
                    {
                        "type": "mark_text",
                        "text": "[3]",
                        "bbox": [
                            508,
                            103,
                            528,
                            118
                        ],
                        "page_number": 4,
                        "is_pre": false,
                        "is_pot_pre": false
                    }
                ],
                "issues": []
            },
            {
                "label": "(b)",
                "page_number": 4,
                "bbox": [
                    69,
                    529,
                    88,
                    544
                ],
                "level": 69,
                "parts": [],
                "content": [
                    {
                        "type": "pre_text",
                        "text": "The random variable \\(X\\) is the number of yellow marbles selected",
                        "bbox": [
                            70,
                            502,
                            379,
                            517
                        ],
                        "page_number": 4,
                        "is_pre": true,
                        "issues": [],
                        "is_pot_pre": true
                    },
                    {
                        "type": "text",
                        "text": "Draw up the probability distribution table for \\(X\\)",
                        "bbox": [
                            93,
                            528,
                            322,
                            544
                        ],
                        "page_number": 4,
                        "is_pre": false,
                        "issues": [],
                        "is_pot_pre": false
                    },
                    {
                        "type": "mark_text",
                        "text": "[3]",
                        "bbox": [
                            508,
                            529,
                            528,
                            544
                        ],
                        "page_number": 4,
                        "is_pre": false,
                        "is_pot_pre": false
                    }
                ],
                "issues": []
            }
        ],
        "content": [
            {
                "type": "text",
                "text": "A bag contains 5 yellow and 4 green marbles. Three marbles are selected at random from the bag, without replacement",
                "bbox": [
                    70,
                    62,
                    548,
                    92
                ],
                "page_number": 4,
                "is_pre": false,
                "issues": [],
                "is_pot_pre": false
            }
        ],
        "issues": [],
        "is_multi": false
    },
    {
        "label": "4",
        "page_number": 6,
        "bbox": [
            45,
            62,
            57,
            78
        ],
        "level": 45,
        "parts": [
            {
                "label": "(a)",
                "page_number": 6,
                "bbox": [
                    69,
                    62,
                    88,
                    78
                ],
                "level": 69,
                "parts": [],
                "content": [
                    {
                        "type": "text",
                        "text": "In how many different ways can the 9 letters of the word TELESCOPE be arranged?",
                        "bbox": [
                            94,
                            62,
                            495,
                            78
                        ],
                        "page_number": 6,
                        "is_pre": false,
                        "issues": [],
                        "is_pot_pre": false
                    },
                    {
                        "type": "mark_text",
                        "text": "[2]",
                        "bbox": [
                            508,
                            62,
                            528,
                            78
                        ],
                        "page_number": 6,
                        "is_pre": false,
                        "is_pot_pre": false
                    }
                ],
                "issues": []
            },
            {
                "label": "(b)",
                "page_number": 6,
                "bbox": [
                    93,
                    266,
                    111,
                    282
                ],
                "level": 93,
                "parts": [],
                "content": [
                    {
                        "type": "text",
                        "text": "In how many different ways can the 9 letters of the word TELESCOPE be arranged so that there are exactly two letters between the T and the C?",
                        "bbox": [
                            94,
                            266,
                            548,
                            294
                        ],
                        "page_number": 6,
                        "is_pre": false,
                        "issues": [],
                        "is_pot_pre": false
                    },
                    {
                        "type": "mark_text",
                        "text": "[4]",
                        "bbox": [
                            508,
                            279,
                            528,
                            295
                        ],
                        "page_number": 6,
                        "is_pre": false,
                        "is_pot_pre": false
                    }
                ],
                "issues": []
            }
        ],
        "content": [],
        "issues": [],
        "is_multi": false
    },
    {
        "label": "5",
        "page_number": 7,
        "bbox": [
            45,
            62,
            55,
            78
        ],
        "level": 45,
        "parts": [
            {
                "label": "(a)",
                "page_number": 7,
                "bbox": [
                    69,
                    101,
                    87,
                    116
                ],
                "level": 69,
                "parts": [],
                "content": [
                    {
                        "type": "text",
                        "text": "Find the probability that, in a 10-day period in October, fewer than 3 days will be wet",
                        "bbox": [
                            94,
                            101,
                            503,
                            117
                        ],
                        "page_number": 7,
                        "is_pre": false,
                        "issues": [],
                        "is_pot_pre": false
                    },
                    {
                        "type": "mark_text",
                        "text": "[3]",
                        "bbox": [
                            508,
                            102,
                            528,
                            117
                        ],
                        "page_number": 7,
                        "is_pre": false,
                        "is_pot_pre": false
                    }
                ],
                "issues": []
            },
            {
                "label": "(b)",
                "page_number": 7,
                "bbox": [
                    69,
                    361,
                    88,
                    376
                ],
                "level": 69,
                "parts": [],
                "content": [
                    {
                        "type": "text",
                        "text": "Find the probability that the first wet day in October is 8 October",
                        "bbox": [
                            93,
                            361,
                            407,
                            376
                        ],
                        "page_number": 7,
                        "is_pre": false,
                        "issues": [],
                        "is_pot_pre": false
                    },
                    {
                        "type": "mark_text",
                        "text": "[2]",
                        "bbox": [
                            508,
                            361,
                            528,
                            376
                        ],
                        "page_number": 7,
                        "is_pre": false,
                        "is_pot_pre": false
                    }
                ],
                "issues": []
            },
            {
                "label": "(c)",
                "page_number": 7,
                "bbox": [
                    93,
                    556,
                    111,
                    571
                ],
                "level": 93,
                "parts": [],
                "content": [
                    {
                        "type": "text",
                        "text": "For 4 randomly chosen years, find the probability that in exactly 1 of these years the first wet day in October is 8 October",
                        "bbox": [
                            111,
                            565,
                            548,
                            592
                        ],
                        "page_number": 7,
                        "is_pre": false,
                        "issues": [],
                        "is_pot_pre": false
                    },
                    {
                        "type": "mark_text",
                        "text": "[2]",
                        "bbox": [
                            508,
                            577,
                            528,
                            592
                        ],
                        "page_number": 7,
                        "is_pre": false,
                        "is_pot_pre": false
                    }
                ],
                "issues": []
            }
        ],
        "content": [
            {
                "type": "text",
                "text": "In a certain region, the probability that any given day in October is wet is 0.16, independently of other days",
                "bbox": [
                    69,
                    62,
                    548,
                    91
                ],
                "page_number": 7,
                "is_pre": false,
                "issues": [],
                "is_pot_pre": false
            }
        ],
        "issues": [],
        "is_multi": false
    },
    {
        "label": "6",
        "page_number": 8,
        "bbox": [
            46,
            62,
            55,
            78
        ],
        "level": 46,
        "parts": [
            {
                "label": "(a)",
                "page_number": 8,
                "bbox": [
                    69,
                    101,
                    87,
                    117
                ],
                "level": 69,
                "parts": [],
                "content": [
                    {
                        "type": "text",
                        "text": "Find the probability that a randomly chosen employee takes more than 28.6 minutes to complete the task",
                        "bbox": [
                            93,
                            101,
                            548,
                            129
                        ],
                        "page_number": 8,
                        "is_pre": false,
                        "issues": [],
                        "is_pot_pre": false
                    },
                    {
                        "type": "mark_text",
                        "text": "[3]",
                        "bbox": [
                            508,
                            114,
                            528,
                            130
                        ],
                        "page_number": 8,
                        "is_pre": false,
                        "is_pot_pre": false
                    }
                ],
                "issues": []
            },
            {
                "label": "(b)",
                "page_number": 8,
                "bbox": [
                    69,
                    428,
                    88,
                    443
                ],
                "level": 69,
                "parts": [],
                "content": [
                    {
                        "type": "text",
                        "text": "20% of employees take longer than \\(t\\) minutes to complete the task",
                        "bbox": [
                            93,
                            428,
                            410,
                            443
                        ],
                        "page_number": 8,
                        "is_pre": false,
                        "issues": [],
                        "is_pot_pre": false
                    },
                    {
                        "type": "text",
                        "text": "Find the value of \\(t\\)",
                        "bbox": [
                            93,
                            455,
                            186,
                            470
                        ],
                        "page_number": 8,
                        "is_pre": false,
                        "issues": [],
                        "is_pot_pre": false
                    },
                    {
                        "type": "mark_text",
                        "text": "[3]",
                        "bbox": [
                            508,
                            455,
                            528,
                            471
                        ],
                        "page_number": 8,
                        "is_pre": false,
                        "is_pot_pre": false
                    }
                ],
                "issues": []
            },
            {
                "label": "(c)",
                "page_number": 9,
                "bbox": [
                    69,
                    62,
                    87,
                    77
                ],
                "level": 69,
                "parts": [],
                "content": [
                    {
                        "type": "text",
                        "text": "Find the probability that the time taken to complete the task by a randomly chosen employee differs from the mean by less than 15.0 minutes",
                        "bbox": [
                            93,
                            62,
                            548,
                            90
                        ],
                        "page_number": 9,
                        "is_pre": false,
                        "issues": [],
                        "is_pot_pre": false
                    },
                    {
                        "type": "mark_text",
                        "text": "[4]",
                        "bbox": [
                            508,
                            73,
                            528,
                            89
                        ],
                        "page_number": 9,
                        "is_pre": false,
                        "is_pot_pre": false
                    }
                ],
                "issues": []
            }
        ],
        "content": [
            {
                "type": "text",
                "text": "The times taken, in minutes, to complete a particular task by employees at a large company are normally distributed with mean 32.2 and standard deviation 9.6",
                "bbox": [
                    68,
                    62,
                    548,
                    90
                ],
                "page_number": 8,
                "is_pre": false,
                "issues": [],
                "is_pot_pre": false
            }
        ],
        "issues": [],
        "is_multi": false
    },
    {
        "label": "7",
        "page_number": 10,
        "bbox": [
            46,
            63,
            56,
            78
        ],
        "level": 46,
        "parts": [
            {
                "label": "(a)",
                "page_number": 10,
                "bbox": [
                    69,
                    148,
                    87,
                    164
                ],
                "level": 69,
                "parts": [],
                "content": [
                    {
                        "type": "text",
                        "text": "On the grid, draw a cumulative frequency graph to represent these results",
                        "bbox": [
                            93,
                            147,
                            445,
                            164
                        ],
                        "page_number": 10,
                        "is_pre": false,
                        "issues": [],
                        "is_pot_pre": false
                    },
                    {
                        "type": "mark_text",
                        "text": "[2]",
                        "bbox": [
                            508,
                            148,
                            528,
                            164
                        ],
                        "page_number": 10,
                        "is_pre": false,
                        "is_pot_pre": false
                    },
                    {
                        "type": "image",
                        "bbox": [
                            83,
                            197,
                            548,
                            662
                        ],
                        "page_number": 10,
                        "is_pre": false,
                        "image": {
                            "caption": "",
                            "page": 10
                        },
                        "is_pot_pre": false
                    }
                ],
                "issues": []
            },
            {
                "label": "(b)",
                "page_number": 11,
                "bbox": [
                    69,
                    62,
                    88,
                    78
                ],
                "level": 69,
                "parts": [],
                "content": [
                    {
                        "type": "text",
                        "text": "Use your graph to estimate the interquartile range of the distances",
                        "bbox": [
                            93,
                            62,
                            410,
                            78
                        ],
                        "page_number": 11,
                        "is_pre": false,
                        "issues": [],
                        "is_pot_pre": false
                    },
                    {
                        "type": "mark_text",
                        "text": "[2]",
                        "bbox": [
                            508,
                            62,
                            528,
                            78
                        ],
                        "page_number": 11,
                        "is_pre": false,
                        "is_pot_pre": false
                    }
                ],
                "issues": []
            },
            {
                "label": "(c)",
                "page_number": 11,
                "bbox": [
                    93,
                    261,
                    110,
                    277
                ],
                "level": 93,
                "parts": [],
                "content": [
                    {
                        "type": "text",
                        "text": "Calculate estimates of the mean and standard deviation of the distances",
                        "bbox": [
                            114,
                            261,
                            435,
                            277
                        ],
                        "page_number": 11,
                        "is_pre": false,
                        "issues": [],
                        "is_pot_pre": false
                    },
                    {
                        "type": "mark_text",
                        "text": "[6]",
                        "bbox": [
                            508,
                            263,
                            528,
                            279
                        ],
                        "page_number": 11,
                        "is_pre": false,
                        "is_pot_pre": false
                    }
                ],
                "issues": []
            }
        ],
        "content": [
            {
                "type": "text",
                "text": "The distances, \\(x \\mathrm{~m}\\), travelled to school by 140 children were recorded. The results are summarised in the table below",
                "bbox": [
                    69,
                    62,
                    548,
                    92
                ],
                "page_number": 10,
                "is_pre": false,
                "issues": [],
                "is_pot_pre": false
            },
            {
                "type": "table",
                "bbox": [
                    84,
                    96,
                    533,
                    136
                ],
                "page_number": 10,
                "is_pre": false,
                "table": {
                    "html": "<table><tr><td>Distance, \\(x \\mathrm{~m}\\)</td><td>\\(x \\leqslant 200\\)</td><td>\\(x \\leqslant 300\\)</td><td>\\(x \\leqslant 500\\)</td><td>\\(x \\leqslant 900\\)</td><td>\\(x \\leqslant 1200\\)</td><td>\\(x \\leqslant 1600\\)</td></tr><tr><td>Cumulative frequency</td><td>16</td><td>46</td><td>88</td><td>122</td><td>134</td><td>140</td></tr></table>"
                },
                "issues": [],
                "is_pot_pre": false
            }
        ],
        "issues": [],
        "is_multi": false
    }
]