{
    "1": {
        "page": 1,
        "raw_output": "<|ref|>text<|/ref|><|det|>[[76, 83, 99, 103]]<|/det|>\n<label>28</label>\n\n<|ref|>text<|/ref|><|det|>[[114, 84, 324, 103]]<|/det|>\nComplete the travel graph\n\n<|ref|>text<|/ref|><|det|>[[106, 123, 139, 142]]<|/det|>\n<label>(iv)</label>\n\n<|ref|>text<|/ref|><|det|>[[144, 123, 173, 144]]<|/det|>\n<label>(c)</label>\n\n<|ref|>text<|/ref|><|det|>[[181, 123, 509, 142]]<|/det|>\n0.15MW B 1.5MW C 1.7MW D 90MW\n\n<|ref|>text<|/ref|><|det|>[[180, 141, 509, 160]]<|/det|>\nhappens to the brightness of each bulb?\n\n<|ref|>text<|/ref|><|det|>[[675, 238, 860, 257]]<|/det|>\n<form>happens = ............ $tz$\n\n<|ref|>text<|/ref|><|det|>[[881, 238, 910, 256]]<|/det|>\n<mark>[8]\n\n<|ref|>text<|/ref|><|det|>[[144, 273, 178, 293]]<|/det|>\n<label>(b)</label>\n\n<|ref|>text<|/ref|><|det|>[[183, 273, 542, 294]]<|/det|>\nCalculate the acceleration between A and B\n\n<|ref|>text<|/ref|><|det|>[[183, 288, 690, 308]]<|/det|>\nthe locus of points which are equidistant from \\(A\\) and from \\(B\\) .\n\n<|ref|>text<|/ref|><|det|>[[181, 308, 489, 327]]<|/det|>\nthe distance between the two villages\n\n<|ref|>text<|/ref|><|det|>[[878, 429, 907, 447]]<|/det|>\n<mark>[8]\n\n<|ref|>text<|/ref|><|det|>[[143, 463, 171, 482]]<|/det|>\n<label>(a)</label>\n\n<|ref|>text<|/ref|><|det|>[[183, 460, 579, 482]]<|/det|>\nComplete the table for the function \\(y = \\frac{6}{x}, x \\neq 0\\)\n\n<|ref|>text<|/ref|><|det|>[[180, 478, 905, 514]]<|/det|>\nare produced by vibrating objects. A certain object vibrates but a person nearby cannot hear any sound\n\n<|ref|>table<|/ref|><|det|>[[450, 520, 697, 588]]<|/det|>\n<table><tr><td>0</td><td>3</td><td>5</td><td>6</td><td>7</td><td>7</td><td>8</td><td>8</td></tr><tr><td>1</td><td>1</td><td>2</td><td>2</td><td>3</td><td>6</td><td>6</td><td>6</td></tr><tr><td>2</td><td>0</td><td></td><td></td><td></td><td></td><td></td><td></td></tr></table>\n\n<|ref|>text<|/ref|><|det|>[[880, 672, 908, 691]]<|/det|>\n<mark>[6]\n\n<|ref|>text<|/ref|><|det|>[[139, 713, 170, 731]]<|/det|>\n<label>(e)</label>\n\n<|ref|>text<|/ref|><|det|>[[183, 713, 356, 731]]<|/det|>\nthe exact value of \\(I_{4}\\)\n\n<|ref|>equation<|/ref|><|det|>[[395, 732, 714, 752]]<|/det|>\n\\[3\\sin^{2}(\\theta +70^{\\circ}) - 8\\cos (\\theta +70^{\\circ}) - 7 = 0\\]\n\n<|ref|>text<|/ref|><|det|>[[739, 853, 861, 873]]<|/det|>\n<form>exact = .... $ih$\n\n<|ref|>text<|/ref|><|det|>[[881, 853, 908, 871]]<|/det|>\n<mark>[5]\n\n<｜end▁of▁sentence｜>"
    },
    "2": {
        "page": 2,
        "raw_output": "<|ref|>text<|/ref|><|det|>[[102, 84, 128, 103]]<|/det|>\n<label>(i)</label>\n\n<|ref|>text<|/ref|><|det|>[[139, 83, 171, 104]]<|/det|>\n<label>(d)</label>\n\n<|ref|>table<|/ref|><|det|>[[309, 100, 829, 211]]<|/det|>\n<table><tr><td></td><td>magnitude of magnetic field</td><td>direction of magnetic field</td></tr><tr><td>A</td><td>increases</td><td>changes</td></tr><tr><td>B</td><td>increases</td><td>unchanged</td></tr><tr><td>C</td><td>unchanged</td><td>changes</td></tr><tr><td>D</td><td>unchanged</td><td>unchanged</td></tr></table>\n\n<|ref|>text<|/ref|><|det|>[[181, 214, 373, 233]]<|/det|>\nestimate is reasonable?\n\n<|ref|>equation<|/ref|><|det|>[[515, 233, 586, 250]]<|/det|>\n\\[p = \\rho gh\\]\n\n<|ref|>text<|/ref|><|det|>[[546, 323, 851, 343]]<|/det|>\n<form>estimate reasonable? = .............. $wk$\n\n<|ref|>text<|/ref|><|det|>[[873, 323, 903, 343]]<|/det|>\n<mark>[5]\n\n<|ref|>text<|/ref|><|det|>[[139, 358, 170, 376]]<|/det|>\n<label>(c)</label>\n\n<|ref|>text<|/ref|><|det|>[[181, 358, 371, 377]]<|/det|>\nShow that \\(p + q = 19\\) .\n\n<|ref|>text<|/ref|><|det|>[[181, 373, 902, 411]]<|/det|>\nincomplete diagram of an amplifier circuit incorporating an ideal operational amplifier is shown in Fig. 8.1\n\n<|ref|>text<|/ref|><|det|>[[875, 504, 905, 524]]<|/det|>\n<mark>[4]\n\n<|ref|>text<|/ref|><|det|>[[106, 542, 138, 559]]<|/det|>\n<label>(v)</label>\n\n<|ref|>text<|/ref|><|det|>[[151, 541, 432, 561]]<|/det|>\nparticle is emitted in this process?\n\n<|ref|>text<|/ref|><|det|>[[596, 643, 861, 662]]<|/det|>\n<form>emitted particle = ................ $ii$\n\n<|ref|>text<|/ref|><|det|>[[881, 643, 910, 661]]<|/det|>\n<mark>[5]\n\n<|ref|>text<|/ref|><|det|>[[79, 686, 106, 704]]<|/det|>\n<label>13</label>\n\n<|ref|>text<|/ref|><|det|>[[121, 683, 487, 704]]<|/det|>\nparagraph correctly describes the molecules?\n\n<｜end▁of▁sentence｜>"
    },
    "3": {
        "page": 3,
        "raw_output": "<|ref|>text<|/ref|><|det|>[[109, 81, 138, 98]]<|/det|>\n<label>(e)</label>\n\n<|ref|>text<|/ref|><|det|>[[144, 81, 171, 101]]<|/det|>\n<label>(i)</label>\n\n<|ref|>text<|/ref|><|det|>[[185, 81, 927, 120]]<|/det|>\ndiagrams are drawn to compare sets of data from each team in a hockey league during a year. Write down the type of correlation you would expect to see when the data recorded is\n\n<|ref|>image<|/ref|><|det|>[[453, 122, 656, 265]]<|/det|>\n\n\n<|ref|>text<|/ref|><|det|>[[673, 367, 853, 387]]<|/det|>\n<form>data = ............... $wx$\n\n<|ref|>text<|/ref|><|det|>[[873, 368, 902, 384]]<|/det|>\n<mark>[6]\n\n<|ref|>text<|/ref|><|det|>[[143, 396, 175, 415]]<|/det|>\n<label>(v)</label>\n\n<|ref|>text<|/ref|><|det|>[[185, 396, 928, 419]]<|/det|>\nP signals to scout Q on the other side of a valley by using a mirror to reflect the Sun's light\n\n<|ref|>text<|/ref|><|det|>[[183, 414, 437, 435]]<|/det|>\nthe power output of the motor\n\n<|ref|>equation<|/ref|><|det|>[[485, 435, 620, 504]]<|/det|>\n\\[u = \\underbrace{25.8\\mathrm{cm}}_{\\mathrm{v} = \\underbrace{36.2\\mathrm{cm}}_{\\mathrm{v} = \\underbrace{36.2\\mathrm{cm}}_{\\text{}}}}\\]\n\n<|ref|>text<|/ref|><|det|>[[698, 612, 861, 632]]<|/det|>\n<form>output = .......... $st$\n\n<|ref|>text<|/ref|><|det|>[[881, 615, 912, 632]]<|/det|>\n<mark>[5]\n\n<|ref|>text<|/ref|><|det|>[[106, 645, 136, 663]]<|/det|>\n<label>(d)</label>\n\n<|ref|>text<|/ref|><|det|>[[139, 644, 168, 664]]<|/det|>\n<label>(v)</label>\n\n<|ref|>text<|/ref|><|det|>[[183, 644, 359, 666]]<|/det|>\nFind \\(\\int (7x - 10)^{-\\frac{3}{5}} \\mathrm{d}x\\)\n\n<|ref|>equation<|/ref|><|det|>[[477, 668, 626, 698]]<|/det|>\n\\[\\frac{\\tan x + \\sin x}{\\tan x - \\sin x} = k,\\]\n\n<|ref|>text<|/ref|><|det|>[[878, 777, 907, 796]]<|/det|>\n<mark>[1]\n\n<｜end▁of▁sentence｜>"
    },
    "4": {
        "page": 4,
        "raw_output": "<|ref|>text<|/ref|><|det|>[[149, 81, 175, 98]]<|/det|>\n<label>(i)</label>\n\n<|ref|>text<|/ref|><|det|>[[190, 79, 332, 98]]<|/det|>\npeople run \\(10\\mathrm{km}\\)\n\n<|ref|>text<|/ref|><|det|>[[188, 98, 379, 119]]<|/det|>\nthe list of factors of 36\n\n<|ref|>equation<|/ref|><|det|>[[477, 122, 641, 141]]<|/det|>\n\\[c = 3.00\\times 10^{8}\\mathrm{m s}^{-1}\\]\n\n<|ref|>text<|/ref|><|det|>[[887, 227, 913, 244]]<|/det|>\n<mark>[6]\n\n<|ref|>text<|/ref|><|det|>[[143, 260, 180, 278]]<|/det|>\n<label>(iv)</label>\n\n<|ref|>text<|/ref|><|det|>[[186, 259, 489, 280]]<|/det|>\nis the new reading on the voltmeter?\n\n<|ref|>text<|/ref|><|det|>[[185, 280, 930, 323]]<|/det|>\na group of students, the numbers of boys and girls studying Art, Music and Drama are given in the following table. Each of these 160 students is studying exactly one of these subjects\n\n<|ref|>text<|/ref|><|det|>[[880, 402, 908, 420]]<|/det|>\n<mark>[4]\n\n<|ref|>text<|/ref|><|det|>[[74, 427, 102, 452]]<|/det|>\n<label>12</label>\n\n<|ref|>text<|/ref|><|det|>[[119, 429, 928, 476]]<|/det|>\nelectric motor being used to supply the power to lift the container is using a current of 240 A at a potential difference of 2200 V\n\n<|ref|>text<|/ref|><|det|>[[118, 471, 935, 516]]<|/det|>\nship of mass \\(8.4 \\times 10^{7} \\mathrm{~kg}\\) is approaching a harbour with speed \\(16.4 \\mathrm{~m} \\mathrm{s}^{- 1}\\) . By using reverse thrust it can maintain a constant total stopping force of \\(920000 \\mathrm{~N}\\)\n\n<|ref|>text<|/ref|><|det|>[[107, 521, 136, 540]]<|/det|>\n<label>(b)</label>\n\n<|ref|>text<|/ref|><|det|>[[149, 521, 902, 561]]<|/det|>\nowner decides to close the café at a later time on Sunday. This increases the total number of hours the café is open by \\(4\\%\\) . Work out the new closing time on Sunday\n\n<|ref|>text<|/ref|><|det|>[[148, 559, 482, 579]]<|/det|>\nproduces an electromotive force (e.m.f.)?\n\n<|ref|>text<|/ref|><|det|>[[620, 656, 853, 676]]<|/det|>\n<form>total decides = ............... $iq$\n\n<|ref|>text<|/ref|><|det|>[[873, 658, 903, 676]]<|/det|>\n<mark>[2]\n\n<|ref|>text<|/ref|><|det|>[[102, 691, 133, 710]]<|/det|>\n<label>(a)</label>\n\n<|ref|>text<|/ref|><|det|>[[136, 691, 173, 710]]<|/det|>\n<label>(iii)</label>\n\n<|ref|>text<|/ref|><|det|>[[178, 691, 915, 732]]<|/det|>\nfriend uses a stopwatch to record the time at the start of the ride, after one circuit, and at the end of the three circuits. The readings from the stopwatch are shown\n\n<|ref|>text<|/ref|><|det|>[[178, 727, 912, 770]]<|/det|>\nof type \\(A\\) are known to have a mean life of 150 hours. It is required to test whether a new type of battery, type \\(B\\) , has a shorter mean life than type \\(A\\) batteries\n\n<|ref|>text<|/ref|><|det|>[[871, 858, 900, 877]]<|/det|>\n<mark>[6]\n\n<｜end▁of▁sentence｜>"
    },
    "5": {
        "page": 5,
        "raw_output": "<|ref|>text<|/ref|><|det|>[[149, 78, 173, 98]]<|/det|>\n<label>(i)</label>\n\n<|ref|>text<|/ref|><|det|>[[190, 79, 725, 103]]<|/det|>\nthe identity \\(2\\sin P\\cos Q = \\sin (P + Q) + \\sin (P - Q)\\) to show that\n\n<|ref|>table<|/ref|><|det|>[[388, 107, 772, 177]]<|/det|>\n<table><tr><td>test</td><td>outcome for alpha</td><td>outcome for beta</td></tr><tr><td></td><td></td><td></td></tr><tr><td></td><td></td><td></td></tr></table>\n\n<|ref|>text<|/ref|><|det|>[[868, 266, 905, 285]]<|/det|>\n<mark>[20]\n\n<|ref|>text<|/ref|><|det|>[[148, 298, 178, 316]]<|/det|>\n<label>(ii)</label>\n\n<|ref|>text<|/ref|><|det|>[[186, 299, 932, 339]]<|/det|>\nSamples of \\(8 \\mathrm{cm}^3\\) of water from \\(A\\) and \\(12 \\mathrm{cm}^3\\) of water from \\(B\\) are taken at random. Find the probability that the total number of bacteria in these samples is at least 3.\n\n<|ref|>text<|/ref|><|det|>[[183, 333, 423, 352]]<|/det|>\nFig. 11.2 shows the Y-plates\n\n<|ref|>text<|/ref|><|det|>[[881, 445, 910, 465]]<|/det|>\n<mark>[5]\n\n<｜end▁of▁sentence｜>"
    },
    "6": {
        "page": 6,
        "raw_output": "<|ref|>text<|/ref|><|det|>[[106, 83, 136, 102]]<|/det|>\n<label>(g)</label>\n\n<|ref|>text<|/ref|><|det|>[[141, 84, 171, 101]]<|/det|>\n<label>(ii)</label>\n\n<|ref|>text<|/ref|><|det|>[[180, 82, 705, 102]]<|/det|>\nDraw a histogram on graph paper to represent this information.\n\n<|ref|>image<|/ref|><|det|>[[306, 107, 798, 453]]<|/det|>\n\n\n<|ref|>text<|/ref|><|det|>[[180, 459, 620, 478]]<|/det|>\nshould the student calculate the density of the stone?\n\n<|ref|>text<|/ref|><|det|>[[871, 554, 913, 573]]<|/det|>\n<mark>[20]\n\n<|ref|>text<|/ref|><|det|>[[146, 593, 171, 613]]<|/det|>\n<label>(i)</label>\n\n<|ref|>text<|/ref|><|det|>[[183, 592, 910, 644]]<|/det|>\nAluminium atoms are spaced widely apart. B Aluminium atoms move more freely than mercury atoms. C Atoms in a liquid take up less space than atoms in a solid. D Mercury atoms have greater mass than aluminium atoms\n\n<|ref|>image<|/ref|><|det|>[[309, 654, 799, 747]]<|/det|>\n\n\n<|ref|>text<|/ref|><|det|>[[690, 821, 850, 840]]<|/det|>\n<form>apart. = ......... $ms$\n\n<|ref|>text<|/ref|><|det|>[[873, 821, 912, 839]]<|/det|>\n<mark>[15]\n\n<｜end▁of▁sentence｜>"
    },
    "7": {
        "page": 7,
        "raw_output": "<|ref|>text<|/ref|><|det|>[[134, 88, 171, 106]]<|/det|>\n<label>(iii)</label>\n\n<|ref|>text<|/ref|><|det|>[[173, 84, 411, 104]]<|/det|>\nthe table for \\(y = 4 + 2x - x^2\\)\n\n<|ref|>text<|/ref|><|det|>[[176, 103, 368, 125]]<|/det|>\nflux intensity = Wm- 2\n\n<|ref|>text<|/ref|><|det|>[[588, 203, 846, 224]]<|/det|>\n<form>table intensity = ................ $aa$\n\n<|ref|>text<|/ref|><|det|>[[868, 203, 897, 222]]<|/det|>\n<mark>[5]\n\n<|ref|>text<|/ref|><|det|>[[101, 249, 129, 269]]<|/det|>\n<label>(c)</label>\n\n<|ref|>text<|/ref|><|det|>[[136, 250, 170, 271]]<|/det|>\n<label>(ii)</label>\n\n<|ref|>text<|/ref|><|det|>[[178, 244, 620, 267]]<|/det|>\npermanent magnet is placed close to a bar of soft iron\n\n<|ref|>image<|/ref|><|det|>[[373, 267, 729, 549]]<|/det|>\n\n\n<|ref|>text<|/ref|><|det|>[[692, 621, 860, 640]]<|/det|>\n<form>placed = ........... $nk$\n\n<|ref|>text<|/ref|><|det|>[[881, 621, 910, 638]]<|/det|>\n<mark>[5]\n\n<｜end▁of▁sentence｜>"
    },
    "8": {
        "page": 8,
        "raw_output": "<|ref|>text<|/ref|><|det|>[[139, 82, 176, 101]]<|/det|>\n<label>(iii)</label>\n\n<|ref|>text<|/ref|><|det|>[[183, 82, 559, 103]]<|/det|>\nP has diameter \\(d\\) and wire Q has diameter \\(2d\\)\n\n<|ref|>table<|/ref|><|det|>[[435, 108, 710, 219]]<|/det|>\n<table><tr><td></td><td>light waves</td><td>radio waves</td></tr><tr><td>A</td><td>longitudinal</td><td>longitudinal</td></tr><tr><td>B</td><td>longitudinal</td><td>transverse</td></tr><tr><td>C</td><td>transverse</td><td>longitudinal</td></tr><tr><td>D</td><td>transverse</td><td>transverse</td></tr></table>\n\n<|ref|>text<|/ref|><|det|>[[183, 218, 910, 254]]<|/det|>\nIt begins to move downwards.  B It begins to move upwards.  C Its speed decreases.  D Its speed increases\n\n<|ref|>text<|/ref|><|det|>[[653, 346, 853, 367]]<|/det|>\n<form>diameter = .............. $qt$\n\n<|ref|>text<|/ref|><|det|>[[875, 346, 905, 365]]<|/det|>\n<mark>[2]\n\n<|ref|>text<|/ref|><|det|>[[148, 380, 171, 399]]<|/det|>\n<label>(i)</label>\n\n<|ref|>text<|/ref|><|det|>[[183, 380, 719, 399]]<|/det|>\na matrix \\(\\mathbf{P}\\) and a diagonal matrix \\(\\mathbf{D}\\) such that \\(\\mathbf{A} - 2\\mathbf{I} = \\mathbf{P}\\mathbf{D}\\mathbf{P}^{-1}\\)\n\n<|ref|>text<|/ref|><|det|>[[183, 400, 473, 418]]<|/det|>\nwhich direction does this force act?\n\n<|ref|>table<|/ref|><|det|>[[329, 419, 813, 532]]<|/det|>\n<table><tr><td></td><td>wavelength<br>5.0 × 10-7 m</td><td>wavelength<br>5.0 × 10-2 m</td></tr><tr><td>A</td><td>ultraviolet</td><td>infrared</td></tr><tr><td>B</td><td>visible</td><td>microwave</td></tr><tr><td>C</td><td>ultraviolet</td><td>microwave</td></tr><tr><td>D</td><td>visible</td><td>infrared</td></tr></table>\n\n<|ref|>text<|/ref|><|det|>[[865, 618, 903, 636]]<|/det|>\n<mark>[12]\n\n<|ref|>text<|/ref|><|det|>[[74, 656, 92, 675]]<|/det|>\n<label>7</label>\n\n<|ref|>text<|/ref|><|det|>[[114, 657, 383, 673]]<|/det|>\nthis statement about the value of \\(n\\)\n\n<｜end▁of▁sentence｜>"
    },
    "9": {
        "page": 9,
        "raw_output": "<|ref|>text<|/ref|><|det|>[[94, 90, 123, 108]]<|/det|>\n<label>(c)</label>\n\n<|ref|>text<|/ref|><|det|>[[134, 74, 910, 126]]<|/det|>\nDraw the straight line of best fit and a worst acceptable straight line on your graph. Both lines should be clearly labelled\n\n<|ref|>table<|/ref|><|det|>[[343, 122, 747, 238]]<|/det|>\n<table><tr><td></td><td>reading on voltmeter</td><td>brightness of lamp</td></tr><tr><td>A</td><td>decreases</td><td>decreases</td></tr><tr><td>B</td><td>decreases</td><td>increases</td></tr><tr><td>C</td><td>increases</td><td>decreases</td></tr><tr><td>D</td><td>increases</td><td>increases</td></tr></table>\n\n<|ref|>text<|/ref|><|det|>[[139, 242, 312, 262]]<|/det|>\nthe exact value of \\(I_{4}\\)\n\n<|ref|>text<|/ref|><|det|>[[865, 331, 903, 350]]<|/det|>\n<mark>[12]\n\n<|ref|>text<|/ref|><|det|>[[102, 377, 131, 395]]<|/det|>\n<label>(b)</label>\n\n<|ref|>text<|/ref|><|det|>[[143, 376, 171, 395]]<|/det|>\n<label>(v)</label>\n\n<|ref|>text<|/ref|><|det|>[[178, 369, 576, 395]]<|/det|>\ndiffraction B dispersion C reflection D refraction\n\n<|ref|>equation<|/ref|><|det|>[[465, 389, 635, 411]]<|/det|>\n\\[1u = 1.66\\times 10^{-27}\\mathrm{kg}\\]\n\n<|ref|>text<|/ref|><|det|>[[866, 502, 905, 522]]<|/det|>\n<mark>[12]\n\n<｜end▁of▁sentence｜>"
    },
    "10": {
        "page": 10,
        "raw_output": "<|ref|>text<|/ref|><|det|>[[149, 78, 185, 98]]<|/det|>\n<label>(iv)</label>\n\n<|ref|>image<|/ref|><|det|>[[212, 106, 897, 587]]<|/det|>\n\n\n<|ref|>text<|/ref|><|det|>[[178, 590, 925, 629]]<|/det|>\nExplain, with reference to gravitational field lines, why the gravitational field near the surface of the Earth is approximately constant for small changes in height\n\n<|ref|>text<|/ref|><|det|>[[668, 710, 848, 730]]<|/det|>\n<form>constant = .......... $rt$\n\n<|ref|>text<|/ref|><|det|>[[865, 711, 907, 731]]<|/det|>\n<mark>[12]\n\n<|ref|>text<|/ref|><|det|>[[76, 737, 101, 756]]<|/det|>\n<label>29</label>\n\n<|ref|>text<|/ref|><|det|>[[114, 738, 426, 758]]<|/det|>\nare the first five terms in a sequence\n\n<｜end▁of▁sentence｜>"
    },
    "11": {
        "page": 11,
        "raw_output": "<|ref|>text<|/ref|><|det|>[[107, 84, 136, 103]]<|/det|>\n<label>(c)</label>\n\n<|ref|>text<|/ref|><|det|>[[144, 83, 175, 103]]<|/det|>\n<label>(ii)</label>\n\n<|ref|>text<|/ref|><|det|>[[183, 85, 442, 102]]<|/det|>\ncurve has parametric equations\n\n<|ref|>text<|/ref|><|det|>[[185, 106, 463, 125]]<|/det|>\n2.1 shows the graph of her results\n\n<|ref|>equation<|/ref|><|det|>[[438, 127, 673, 145]]<|/det|>\n\\[\\mathrm{p}(x) = 2x^{3} - 3x^{2} - 23x + 12\\]\n\n<|ref|>text<|/ref|><|det|>[[875, 231, 905, 248]]<|/det|>\n<mark>[5]\n\n<|ref|>text<|/ref|><|det|>[[139, 268, 173, 286]]<|/det|>\n<label>(v)</label>\n\n<|ref|>text<|/ref|><|det|>[[185, 267, 925, 333]]<|/det|>\nof light in free space permeability of free space permittivity of free space elementary charge the Planck constant unified atomic mass unit rest mass of electron rest mass of proton molar gas constant the Avogadro constant the Boltzmann constant gravitational constant acceleration of free fall\n\n<|ref|>text<|/ref|><|det|>[[183, 338, 509, 356]]<|/det|>\nthe solution to the differential equation\n\n<|ref|>text<|/ref|><|det|>[[594, 429, 858, 448]]<|/det|>\n<form>Avogadro space = ............... $br$\n\n<|ref|>text<|/ref|><|det|>[[876, 429, 907, 448]]<|/det|>\n<mark>[4]\n\n<|ref|>text<|/ref|><|det|>[[107, 463, 138, 482]]<|/det|>\n<label>(a)</label>\n\n<|ref|>text<|/ref|><|det|>[[146, 464, 171, 482]]<|/det|>\n<label>(i)</label>\n\n<|ref|>text<|/ref|><|det|>[[183, 464, 913, 498]]<|/det|>\nhow the gradient of the curve at the point \\(A\\) can be deduced from the answer to part (a), and state the value of this gradient.\n\n<|ref|>equation<|/ref|><|det|>[[512, 501, 596, 518]]<|/det|>\n\\[a = -\\omega^2 x\\]\n\n<|ref|>text<|/ref|><|det|>[[638, 610, 860, 630]]<|/det|>\n<form>gradient. = .................. $cv$\n\n<|ref|>text<|/ref|><|det|>[[883, 611, 910, 630]]<|/det|>\n<mark>[5]\n\n<｜end▁of▁sentence｜>"
    },
    "12": {
        "page": 12,
        "raw_output": "<|ref|>text<|/ref|><|det|>[[144, 84, 183, 103]]<|/det|>\n<label>(iii)</label>\n\n<|ref|>image<|/ref|><|det|>[[425, 109, 683, 289]]<|/det|>\n\n\n<|ref|>text<|/ref|><|det|>[[183, 297, 917, 331]]<|/det|>\nwavefront AB is travelling in region P towards region Q, where the water is shallower and the waves travel more slowly\n\n<|ref|>text<|/ref|><|det|>[[567, 422, 846, 439]]<|/det|>\n<form>slowly towards travelling = .... $ni$\n\n<|ref|>text<|/ref|><|det|>[[868, 422, 907, 440]]<|/det|>\n<mark>[15]\n\n<|ref|>text<|/ref|><|det|>[[146, 457, 178, 475]]<|/det|>\n<label>(ii)</label>\n\n<|ref|>text<|/ref|><|det|>[[185, 458, 930, 492]]<|/det|>\ncurrent in the LDR is \\(I_{1}\\) and the current in the \\(800\\Omega\\) resistor is \\(I_{2}\\) . Complete the equation that relates the current in the \\(450\\Omega\\) resistor to \\(I_{1}\\) and \\(I_{2}\\) . current in the \\(450\\Omega\\) resistor =\n\n<|ref|>text<|/ref|><|det|>[[183, 494, 766, 513]]<|/det|>\ntable shows the number of items sold to each of 60 customers in a shop\n\n<|ref|>text<|/ref|><|det|>[[185, 513, 432, 532]]<|/det|>\nFind the greatest speed of \\(P\\) .\n\n<|ref|>text<|/ref|><|det|>[[883, 613, 910, 632]]<|/det|>\n<mark>[5]\n\n<|ref|>text<|/ref|><|det|>[[106, 654, 138, 672]]<|/det|>\n<label>(b)</label>\n\n<|ref|>text<|/ref|><|det|>[[141, 653, 171, 672]]<|/det|>\n<label>(ii)</label>\n\n<|ref|>text<|/ref|><|det|>[[185, 651, 507, 670]]<|/det|>\nthat the curve with Cartesian equation\n\n<|ref|>text<|/ref|><|det|>[[183, 670, 593, 688]]<|/det|>\nstudent investigates the image produced by a lens\n\n<|ref|>text<|/ref|><|det|>[[885, 776, 913, 795]]<|/det|>\n<mark>[4]\n\n<｜end▁of▁sentence｜>"
    },
    "13": {
        "page": 13,
        "raw_output": "<|ref|>text<|/ref|><|det|>[[144, 84, 181, 103]]<|/det|>\n<label>(iv)</label>\n\n<|ref|>text<|/ref|><|det|>[[183, 83, 354, 103]]<|/det|>\nCalculate \\((V_{\\mathrm{A}} + V_{\\mathrm{B}})\\)\n\n<|ref|>text<|/ref|><|det|>[[183, 106, 928, 158]]<|/det|>\nwires, P and Q, have the same resistance. Wire Q is made of material that has twice the resistivity of the material used to make wire P. The diameter of wire Q is twice the diameter of wire P\n\n<|ref|>text<|/ref|><|det|>[[875, 242, 903, 260]]<|/det|>\n<mark>[4]\n\n<|ref|>text<|/ref|><|det|>[[143, 281, 168, 300]]<|/det|>\n<label>(i)</label>\n\n<|ref|>text<|/ref|><|det|>[[185, 281, 420, 299]]<|/det|>\nout the mass of Toni's apple\n\n<|ref|>text<|/ref|><|det|>[[185, 300, 426, 318]]<|/det|>\n1.1 shows the apparatus used\n\n<|ref|>text<|/ref|><|det|>[[881, 407, 915, 422]]<|/det|>\n<mark>[6]\n\n<|ref|>text<|/ref|><|det|>[[143, 438, 173, 456]]<|/det|>\n<label>(v)</label>\n\n<|ref|>text<|/ref|><|det|>[[183, 437, 487, 456]]<|/det|>\nthe combination of springs, calculate\n\n<|ref|>text<|/ref|><|det|>[[183, 456, 927, 507]]<|/det|>\nA sample of aluminium foil has a thickness of \\(0.090 \\text{mm}\\) . The current in the foil is \\(4.6 \\text{A}\\) . A uniform magnetic field of flux density \\(0.15 \\text{T}\\) acts at right-angles to the foil. Use the value in (i) to calculate the voltage \\(V_{\\text{H}}\\) that is generated\n\n<|ref|>text<|/ref|><|det|>[[715, 597, 860, 615]]<|/det|>\n<form>voltage = ..... $yr$\n\n<|ref|>text<|/ref|><|det|>[[880, 596, 910, 613]]<|/det|>\n<mark>[5]\n\n<|ref|>text<|/ref|><|det|>[[81, 630, 106, 649]]<|/det|>\n<label>11</label>\n\n<|ref|>text<|/ref|><|det|>[[121, 630, 504, 648]]<|/det|>\n5.1 shows an electric heater used to heat a room\n\n<|ref|>text<|/ref|><|det|>[[123, 648, 939, 682]]<|/det|>\nbag contains only red, yellow and blue counters. Bashira picks a counter at random from the bag, records its colour, and puts it back in the bag. She does this 60 times\n\n<|ref|>text<|/ref|><|det|>[[121, 687, 381, 705]]<|/det|>\n0.50N B 1.00N C 500N D 1000N\n\n<|ref|>equation<|/ref|><|det|>[[416, 707, 638, 725]]<|/det|>\n\\[x^{4} + x^{3} + 3x^{2} + px + q = 0\\]\n\n<｜end▁of▁sentence｜>"
    },
    "14": {
        "page": 14,
        "raw_output": "<|ref|>text<|/ref|><|det|>[[109, 84, 134, 103]]<|/det|>\n<label>(f)</label>\n\n<|ref|>text<|/ref|><|det|>[[148, 85, 183, 102]]<|/det|>\n<label>(iii)</label>\n\n<|ref|>image<|/ref|><|det|>[[326, 107, 784, 303]]<|/det|>\n\n\n<|ref|>text<|/ref|><|det|>[[183, 313, 653, 332]]<|/det|>\nthe percentage of energy transferred as electrical working\n\n<|ref|>text<|/ref|><|det|>[[589, 396, 855, 415]]<|/det|>\n<form>percentage percentage = .... $wu$\n\n<|ref|>text<|/ref|><|det|>[[875, 395, 905, 415]]<|/det|>\n<mark>[2]\n\n<|ref|>text<|/ref|><|det|>[[146, 434, 176, 452]]<|/det|>\n<label>(ii)</label>\n\n<|ref|>table<|/ref|><|det|>[[442, 452, 707, 496]]<|/det|>\n<table><tr><td>x</td><td>-1</td><td>0</td><td>1</td><td>2</td><td>3</td><td>4</td><td>5</td></tr><tr><td>y</td><td></td><td>3</td><td>-1</td><td></td><td></td><td>-1</td><td>3</td></tr></table>\n\n<|ref|>text<|/ref|><|det|>[[185, 496, 829, 515]]<|/det|>\ntime taken by \\(P\\) to travel from the top to the bottom of the plane is \\(T\\) seconds\n\n<|ref|>image<|/ref|><|det|>[[319, 523, 791, 706]]<|/det|>\n\n\n<|ref|>text<|/ref|><|det|>[[878, 797, 907, 817]]<|/det|>\n<mark>[6]\n\n<｜end▁of▁sentence｜>"
    },
    "15": {
        "page": 15,
        "raw_output": "<|ref|>text<|/ref|><|det|>[[141, 83, 166, 102]]<|/det|>\n<label>(i)</label>\n\n<|ref|>text<|/ref|><|det|>[[185, 85, 369, 103]]<|/det|>\nis the output voltage?\n\n<|ref|>table<|/ref|><|det|>[[329, 106, 818, 152]]<|/det|>\n<table><tr><td>Day</td><td>Mon</td><td>Tue</td><td>Wed</td><td>Thu</td><td>Fri</td><td>Sat</td><td>Sun</td></tr><tr><td>Takings ($)</td><td>153</td><td>201</td><td>178</td><td>231</td><td>164</td><td>147</td><td>156</td></tr></table>\n\n<|ref|>text<|/ref|><|det|>[[185, 153, 826, 173]]<|/det|>\nstudent suggests that the resistance \\(R\\) of the lamp filament should be constant\n\n<|ref|>text<|/ref|><|det|>[[603, 248, 860, 266]]<|/det|>\n<form>resistance suggests = ......... $xd$\n\n<|ref|>text<|/ref|><|det|>[[881, 247, 912, 266]]<|/det|>\n<mark>[8]\n\n<|ref|>text<|/ref|><|det|>[[107, 280, 138, 298]]<|/det|>\n<label>(d)</label>\n\n<|ref|>image<|/ref|><|det|>[[262, 297, 814, 547]]<|/det|>\n\n\n<|ref|>text<|/ref|><|det|>[[149, 554, 504, 572]]<|/det|>\nthe cumulative distribution function of \\(X\\) .\n\n<|ref|>table<|/ref|><|det|>[[437, 577, 673, 622]]<|/det|>\n<table><tr><td>x</td><td>0.9</td><td>1.6</td><td>2.4</td><td>3.2</td></tr><tr><td>ln y</td><td>1.7</td><td>1.9</td><td>2.3</td><td>2.6</td></tr></table>\n\n<|ref|>text<|/ref|><|det|>[[883, 714, 913, 734]]<|/det|>\n<mark>[8]\n\n<|ref|>text<|/ref|><|det|>[[107, 752, 139, 771]]<|/det|>\n<label>(a)</label>\n\n<|ref|>text<|/ref|><|det|>[[149, 752, 897, 771]]<|/det|>\nthe Earth, hydrogen in the laboratory emits electromagnetic radiation of wavelength \\(656 \\text{nm}\\)\n\n<|ref|>text<|/ref|><|det|>[[866, 852, 907, 870]]<|/det|>\n<mark>[15]\n\n<｜end▁of▁sentence｜>"
    },
    "16": {
        "page": 16,
        "raw_output": "<|ref|>text<|/ref|><|det|>[[107, 84, 139, 102]]<|/det|>\n<label>(b)</label>\n\n<|ref|>text<|/ref|><|det|>[[151, 83, 927, 135]]<|/det|>\nstudent places the metre rule on the pivot at the \\(50.0\\mathrm{cm}\\) mark and then places block U with its centre at the \\(5.0\\mathrm{cm}\\) mark. Suggest why it might be difficult to place block U accurately at the \\(5.0\\mathrm{cm}\\) mark. Explain how the student could overcome this difficulty. You may draw a diagram\n\n<|ref|>text<|/ref|><|det|>[[149, 135, 509, 154]]<|/det|>\nwhen the load has maximum kinetic energy\n\n<|ref|>text<|/ref|><|det|>[[717, 238, 858, 257]]<|/det|>\n<form>mark. = ...... $sg$\n\n<|ref|>text<|/ref|><|det|>[[878, 237, 907, 256]]<|/det|>\n<mark>[6]\n\n<|ref|>text<|/ref|><|det|>[[82, 275, 106, 295]]<|/det|>\n<label>11</label>\n\n<|ref|>text<|/ref|><|det|>[[121, 276, 927, 310]]<|/det|>\nlight, conducting ball is at rest on a metal table. When the rod is brought close to the ball, as shown in Fig. 7.1, the ball jumps up towards the rod\n\n<|ref|>text<|/ref|><|det|>[[107, 324, 136, 342]]<|/det|>\n<label>(c)</label>\n\n<|ref|>text<|/ref|><|det|>[[139, 324, 166, 343]]<|/det|>\n<label>(i)</label>\n\n<|ref|>text<|/ref|><|det|>[[183, 324, 927, 374]]<|/det|>\na laboratory experiment to test the relationship between \\(a\\) and \\(\\theta\\) . Explain how your results could be used to determine a value for \\(k\\) . You should draw a diagram, on page 3, showing the arrangement of your equipment. In your account you should pay particular attention to\n\n<|ref|>text<|/ref|><|det|>[[183, 374, 343, 393]]<|/det|>\nFind the value of \\(\\theta\\)\n\n<|ref|>image<|/ref|><|det|>[[374, 400, 735, 591]]<|/det|>\n\n\n<|ref|>text<|/ref|><|det|>[[665, 689, 855, 708]]<|/det|>\n<form>value = ................. $uz$\n\n<|ref|>text<|/ref|><|det|>[[876, 689, 905, 707]]<|/det|>\n<mark>[6]\n\n<|ref|>text<|/ref|><|det|>[[141, 727, 180, 747]]<|/det|>\n<label>(iv)</label>\n\n<|ref|>text<|/ref|><|det|>[[183, 727, 386, 745]]<|/det|>\nthe probability that it is\n\n<|ref|>text<|/ref|><|det|>[[185, 751, 781, 769]]<|/det|>\nComplete the frequency table. You may use the tally column to help you\n\n<|ref|>text<|/ref|><|det|>[[693, 834, 860, 853]]<|/det|>\n<form>tally help = ...... $xp$\n\n<|ref|>text<|/ref|><|det|>[[883, 835, 912, 852]]<|/det|>\n<mark>[8]\n\n<｜end▁of▁sentence｜>"
    },
    "17": {
        "page": 17,
        "raw_output": "<|ref|>text<|/ref|><|det|>[[144, 83, 175, 102]]<|/det|>\n<label>(v)</label>\n\n<|ref|>text<|/ref|><|det|>[[185, 84, 396, 103]]<|/det|>\ndown all the factors of 18\n\n<|ref|>equation<|/ref|><|det|>[[423, 104, 687, 122]]<|/det|>\n\\[\\mathrm{g}(x) = \\mathrm{e}^{x}\\quad \\mathrm{and}\\quad \\mathrm{h}(x) = 5x + 2.\\]\n\n<|ref|>text<|/ref|><|det|>[[682, 210, 863, 229]]<|/det|>\n<form>factors = ............. $ye$\n\n<|ref|>text<|/ref|><|det|>[[883, 211, 912, 230]]<|/det|>\n<mark>[3]\n\n<|ref|>text<|/ref|><|det|>[[109, 249, 138, 267]]<|/det|>\n<label>(a)</label>\n\n<|ref|>text<|/ref|><|det|>[[151, 249, 336, 267]]<|/det|>\nthe circuit of Fig. 7.1:\n\n<|ref|>text<|/ref|><|det|>[[712, 365, 845, 384]]<|/det|>\n<form>circuit = .... $da$\n\n<|ref|>text<|/ref|><|det|>[[865, 367, 905, 384]]<|/det|>\n<mark>[12]\n\n<|ref|>text<|/ref|><|det|>[[107, 401, 138, 419]]<|/det|>\n<label>(b)</label>\n\n<|ref|>text<|/ref|><|det|>[[149, 400, 897, 437]]<|/det|>\nUse an iterative formula based on the equation in part (i) to find the value of \\(a\\) correct to 3 significant figures. Give the result of each iteration to 5 significant figures.\n\n<|ref|>text<|/ref|><|det|>[[151, 438, 418, 458]]<|/det|>\nwire has the greatest resistance?\n\n<|ref|>text<|/ref|><|det|>[[749, 556, 856, 574]]<|/det|>\n<form>find = .... $id$\n\n<|ref|>text<|/ref|><|det|>[[880, 555, 908, 574]]<|/det|>\n<mark>[4]\n\n<|ref|>text<|/ref|><|det|>[[77, 590, 104, 609]]<|/det|>\n<label>10</label>\n\n<|ref|>text<|/ref|><|det|>[[119, 590, 504, 609]]<|/det|>\nthe general solution of the differential equation\n\n<|ref|>text<|/ref|><|det|>[[107, 629, 139, 649]]<|/det|>\n<label>(d)</label>\n\n<|ref|>text<|/ref|><|det|>[[148, 630, 183, 649]]<|/det|>\n<label>(iv)</label>\n\n<|ref|>text<|/ref|><|det|>[[185, 630, 922, 682]]<|/det|>\nthe batteries initially fully charged, the car is driven \\(100km\\) in 'normal driving conditions'. The batteries are then recharged from a household electrical supply delivering a constant current of \\(13.0A\\) at a potential difference (p.d.) of \\(230V\\)\n\n<|ref|>equation<|/ref|><|det|>[[450, 683, 660, 701]]<|/det|>\n\\[3x + y = 5,\\] \\[7x + 3y = 11.\\]\n\n<|ref|>text<|/ref|><|det|>[[883, 783, 912, 801]]<|/det|>\n<mark>[5]\n\n<｜end▁of▁sentence｜>"
    },
    "18": {
        "page": 18,
        "raw_output": "<|ref|>text<|/ref|><|det|>[[141, 84, 168, 103]]<|/det|>\n<label>(i)</label>\n\n<|ref|>image<|/ref|><|det|>[[309, 106, 799, 447]]<|/det|>\n\n\n<|ref|>text<|/ref|><|det|>[[185, 456, 897, 490]]<|/det|>\nspring is extended by applying a force. The variation with extension \\(x\\) of the force \\(F\\) is shown in Fig. 4.1 for the range of values of \\(x\\) from \\(20 \\text{cm}\\) to \\(40 \\text{cm}\\)\n\n<|ref|>text<|/ref|><|det|>[[873, 578, 905, 597]]<|/det|>\n<mark>[3]\n\n<|ref|>text<|/ref|><|det|>[[144, 616, 176, 634]]<|/det|>\n<label>(ii)</label>\n\n<|ref|>text<|/ref|><|det|>[[185, 610, 447, 634]]<|/det|>\nHence find \\(\\int \\frac{\\ln a^{\\sin(2x+5)}+\\ln\\left(\\frac{1}{a}\\right)}{\\ln a} \\mathrm{d}x\\)\n\n<|ref|>equation<|/ref|><|det|>[[505, 635, 603, 654]]<|/det|>\n\\[\\nu = \\sqrt[3]{p + r}\\]\n\n<|ref|>text<|/ref|><|det|>[[185, 657, 492, 676]]<|/det|>\nIn which interval is the median time?\n\n<|ref|>text<|/ref|><|det|>[[698, 772, 858, 791]]<|/det|>\n<form>find = .............. $ir$\n\n<|ref|>text<|/ref|><|det|>[[878, 775, 908, 791]]<|/det|>\n<mark>[6]\n\n<｜end▁of▁sentence｜>"
    },
    "19": {
        "page": 19,
        "raw_output": "<|ref|>text<|/ref|><|det|>[[106, 84, 136, 102]]<|/det|>\n<label>(f)</label>\n\n<|ref|>text<|/ref|><|det|>[[146, 84, 173, 103]]<|/det|>\n<label>(i)</label>\n\n<|ref|>text<|/ref|><|det|>[[183, 85, 410, 102]]<|/det|>\nDescribe one use of X-rays.\n\n<|ref|>equation<|/ref|><|det|>[[448, 104, 662, 123]]<|/det|>\n\\[3t^{2} - (2m + 6)t - 4m = 0\\]\n\n<|ref|>text<|/ref|><|det|>[[662, 235, 846, 252]]<|/det|>\n<form>X-rays. = ............. $ba$\n\n<|ref|>text<|/ref|><|det|>[[870, 234, 910, 253]]<|/det|>\n<mark>[10]\n\n<|ref|>text<|/ref|><|det|>[[144, 268, 180, 287]]<|/det|>\n<label>(iii)</label>\n\n<|ref|>text<|/ref|><|det|>[[185, 269, 420, 287]]<|/det|>\napparatus available includes:\n\n<|ref|>image<|/ref|><|det|>[[185, 300, 928, 507]]<|/det|>\n\n\n<|ref|>text<|/ref|><|det|>[[677, 597, 863, 615]]<|/det|>\n<form>apparatus = ........ $wu$\n\n<|ref|>text<|/ref|><|det|>[[883, 594, 913, 615]]<|/det|>\n<mark>[4]\n\n<|ref|>text<|/ref|><|det|>[[77, 628, 106, 648]]<|/det|>\n<label>24</label>\n\n<|ref|>text<|/ref|><|det|>[[119, 629, 930, 666]]<|/det|>\nthird student releases the ball from a height of \\(85cm\\) on to a concrete floor and it bounces to a height of \\(75cm\\)\n\n<|ref|>text<|/ref|><|det|>[[107, 676, 139, 695]]<|/det|>\n<label>(d)</label>\n\n<|ref|>text<|/ref|><|det|>[[144, 677, 170, 695]]<|/det|>\n<label>(i)</label>\n\n<|ref|>text<|/ref|><|det|>[[186, 674, 762, 695]]<|/det|>\nFor the case where \\(p = 9\\) , find the unit vector in the direction of \\(\\overrightarrow{XP}\\) .\n\n<|ref|>text<|/ref|><|det|>[[183, 694, 485, 713]]<|/det|>\nthe first three terms of this sequence\n\n<|ref|>text<|/ref|><|det|>[[683, 787, 856, 806]]<|/det|>\n<form>sequence = ....... $xw$\n\n<|ref|>text<|/ref|><|det|>[[876, 787, 907, 806]]<|/det|>\n<mark>[8]\n\n<｜end▁of▁sentence｜>"
    },
    "20": {
        "page": 20,
        "raw_output": "<|ref|>text<|/ref|><|det|>[[144, 84, 180, 103]]<|/det|>\n<label>(iii)</label>\n\n<|ref|>text<|/ref|><|det|>[[185, 83, 809, 103]]<|/det|>\nUse the properties of stationary waves to explain these changes in amplitude\n\n<|ref|>table<|/ref|><|det|>[[435, 108, 712, 197]]<|/det|>\n<table><tr><td>object</td><td>mass/g</td><td>volume/cm³</td></tr><tr><td>P</td><td>23</td><td>36</td></tr><tr><td>Q</td><td>170</td><td>720</td></tr><tr><td>R</td><td>240</td><td>340</td></tr></table>\n\n<|ref|>text<|/ref|><|det|>[[881, 282, 910, 300]]<|/det|>\n<mark>[5]\n\n<|ref|>text<|/ref|><|det|>[[143, 323, 173, 341]]<|/det|>\n<label>(ii)</label>\n\n<|ref|>text<|/ref|><|det|>[[183, 322, 727, 341]]<|/det|>\nvariables \\(x, y\\) and \\(z\\) can take only positive values and are such that\n\n<|ref|>text<|/ref|><|det|>[[183, 342, 447, 361]]<|/det|>\nfollowing apparatus is available:\n\n<|ref|>text<|/ref|><|det|>[[734, 443, 856, 462]]<|/det|>\n<form>such = ..... $dh$\n\n<|ref|>text<|/ref|><|det|>[[878, 443, 907, 462]]<|/det|>\n<mark>[6]\n\n<|ref|>text<|/ref|><|det|>[[107, 479, 138, 497]]<|/det|>\n<label>(a)</label>\n\n<|ref|>text<|/ref|><|det|>[[149, 478, 341, 497]]<|/det|>\na mark for this student\n\n<|ref|>text<|/ref|><|det|>[[683, 581, 848, 599]]<|/det|>\n<form>student = ......... $po$\n\n<|ref|>text<|/ref|><|det|>[[868, 580, 910, 598]]<|/det|>\n<mark>[12]\n\n<|ref|>text<|/ref|><|det|>[[107, 616, 139, 634]]<|/det|>\n<label>(b)</label>\n\n<|ref|>text<|/ref|><|det|>[[144, 616, 170, 634]]<|/det|>\n<label>(i)</label>\n\n<|ref|>text<|/ref|><|det|>[[183, 615, 928, 649]]<|/det|>\nthe grid, complete the net of the box. The base and one face of the box have been drawn for you\n\n<|ref|>table<|/ref|><|det|>[[341, 657, 806, 798]]<|/det|>\n<table><tr><td></td><td>refractive index as concentration increases</td><td>speed through solution as concentration increases</td></tr><tr><td>A</td><td>decreases</td><td>decreases</td></tr><tr><td>B</td><td>decreases</td><td>increases</td></tr><tr><td>C</td><td>increases</td><td>decreases</td></tr><tr><td>D</td><td>increases</td><td>increases</td></tr></table>\n\n<|ref|>text<|/ref|><|det|>[[883, 861, 912, 880]]<|/det|>\n<mark>[4]\n\n<｜end▁of▁sentence｜>"
    },
    "21": {
        "page": 21,
        "raw_output": "<|ref|>text<|/ref|><|det|>[[146, 84, 181, 103]]<|/det|>\n<label>(iii)</label>\n\n<|ref|>image<|/ref|><|det|>[[183, 102, 928, 324]]<|/det|>\n\n\n<|ref|>text<|/ref|><|det|>[[185, 336, 564, 352]]<|/det|>\nwaves consist of compressions and rarefactions\n\n<|ref|>text<|/ref|><|det|>[[881, 426, 912, 445]]<|/det|>\n<mark>[3]\n\n<|ref|>text<|/ref|><|det|>[[74, 462, 101, 483]]<|/det|>\n<label>25</label>\n\n<|ref|>text<|/ref|><|det|>[[118, 462, 925, 518]]<|/det|>\nobject accelerates uniformly from rest to speed \\(v\\) . It then moves at constant speed \\(v\\) for a time of 8.0 s before decelerating uniformly to rest. The total time taken is 12.0 s, and the total distance travelled is 60 m\n\n<|ref|>text<|/ref|><|det|>[[109, 530, 136, 549]]<|/det|>\n<label>(c)</label>\n\n<|ref|>text<|/ref|><|det|>[[144, 532, 176, 548]]<|/det|>\n<label>(ii)</label>\n\n<|ref|>text<|/ref|><|det|>[[185, 532, 732, 549]]<|/det|>\nhand held near side Y feels warmer than the hand held near side X\n\n<|ref|>text<|/ref|><|det|>[[185, 546, 923, 581]]<|/det|>\nwire is fixed at one end and is extended by a force \\(F_{1}\\) acting on the other end. This causes the wire to have an elastic potential energy of \\(0.15 \\mathrm{~J}\\)\n\n<|ref|>text<|/ref|><|det|>[[878, 657, 905, 676]]<|/det|>\n<mark>[2]\n\n<｜end▁of▁sentence｜>"
    },
    "22": {
        "page": 22,
        "raw_output": "<|ref|>text<|/ref|><|det|>[[138, 83, 175, 103]]<|/det|>\n<label>(iii)</label>\n\n<|ref|>image<|/ref|><|det|>[[457, 107, 653, 248]]<|/det|>\n\n\n<|ref|>text<|/ref|><|det|>[[185, 260, 366, 279]]<|/det|>\nd. across resistor = V\n\n<|ref|>image<|/ref|><|det|>[[223, 284, 887, 524]]<|/det|>\n\n\n<|ref|>text<|/ref|><|det|>[[650, 603, 860, 621]]<|/det|>\n<form>resistor = .................. $hg$\n\n<|ref|>text<|/ref|><|det|>[[880, 603, 910, 621]]<|/det|>\n<mark>[8]\n\n<|ref|>text<|/ref|><|det|>[[143, 642, 173, 660]]<|/det|>\n<label>(v)</label>\n\n<|ref|>text<|/ref|><|det|>[[185, 642, 923, 676]]<|/det|>\nthe probability that this student passes the science test but does not pass the mathematics test\n\n<|ref|>text<|/ref|><|det|>[[185, 677, 893, 713]]<|/det|>\nvariation with time \\(t\\) (measured in seconds) of the current \\(I\\) (measured in amps) in the resistor is given by the expression\n\n<|ref|>text<|/ref|><|det|>[[885, 798, 913, 817]]<|/det|>\n<mark>[6]\n\n<｜end▁of▁sentence｜>"
    },
    "23": {
        "page": 23,
        "raw_output": "<|ref|>text<|/ref|><|det|>[[109, 84, 138, 102]]<|/det|>\n<label>(b)</label>\n\n<|ref|>text<|/ref|><|det|>[[141, 84, 173, 102]]<|/det|>\n<label>(ii)</label>\n\n<|ref|>text<|/ref|><|det|>[[185, 83, 907, 103]]<|/det|>\nThe free electrons (charge carriers) in the wire have an average drift speed of \\(0.16 \\text{mm} \\text{s}^{-1}\\)\n\n<|ref|>equation<|/ref|><|det|>[[507, 106, 601, 132]]<|/det|>\n\\[W = \\frac{1}{2} QV\\]\n\n<|ref|>text<|/ref|><|det|>[[873, 227, 907, 244]]<|/det|>\n<mark>[6]\n\n<|ref|>text<|/ref|><|det|>[[146, 265, 180, 284]]<|/det|>\n<label>(iv)</label>\n\n<|ref|>image<|/ref|><|det|>[[250, 287, 860, 679]]<|/det|>\n\n\n<|ref|>text<|/ref|><|det|>[[183, 689, 604, 710]]<|/det|>\nDuring the journey, the family stops for 10 minutes\n\n<|ref|>text<|/ref|><|det|>[[878, 814, 908, 832]]<|/det|>\n<mark>[8]\n\n<|ref|>text<|/ref|><|det|>[[79, 851, 104, 868]]<|/det|>\n<label>25</label>\n\n<|ref|>text<|/ref|><|det|>[[121, 846, 631, 871]]<|/det|>\nsolve the equation \\(\\frac{\\cos\\frac{\\theta}{2}}{1 - \\sin\\frac{\\theta}{2}} +\\frac{1 - \\sin\\frac{\\theta}{2}}{\\cos\\frac{\\theta}{2}} = 8\\cos^2\\frac{\\theta}{2}\\) for \\(-360^{\\circ} < \\theta < 360^{\\circ}.\\)\n\n<｜end▁of▁sentence｜>"
    },
    "24": {
        "page": 24,
        "raw_output": "<|ref|>text<|/ref|><|det|>[[109, 84, 139, 103]]<|/det|>\n<label>(a)</label>\n\n<|ref|>text<|/ref|><|det|>[[149, 84, 928, 119]]<|/det|>\ncar has mass \\(m\\) . A person needs to push the car with force \\(F\\) in order to give the car acceleration \\(a\\) . The person needs to push the car with force \\(2F\\) in order to give the car acceleration \\(3a\\)\n\n<|ref|>text<|/ref|><|det|>[[151, 123, 378, 142]]<|/det|>\nstatement must be correct?\n\n<|ref|>text<|/ref|><|det|>[[677, 233, 855, 250]]<|/det|>\n<form>with = ............... $om$\n\n<|ref|>text<|/ref|><|det|>[[878, 233, 905, 250]]<|/det|>\n<mark>[6]\n\n<|ref|>text<|/ref|><|det|>[[107, 271, 138, 289]]<|/det|>\n<label>(d)</label>\n\n<|ref|>text<|/ref|><|det|>[[151, 269, 656, 289]]<|/det|>\nthe average rate of cooling \\(R_{1}\\) of the water using the equation\n\n<|ref|>text<|/ref|><|det|>[[151, 286, 918, 320]]<|/det|>\nheights of plants of type \\(B\\) have mean \\(0.6\\mathrm{m}\\) and standard deviation \\(0.02\\mathrm{m}\\) . A random sample of 5 plants of type \\(B\\) is selected. The sum of the heights of these 5 plants is denoted by \\(H_{B}\\mathrm{m}\\)\n\n<|ref|>text<|/ref|><|det|>[[685, 409, 860, 429]]<|/det|>\n<form>type = .............. $aw$\n\n<|ref|>text<|/ref|><|det|>[[880, 411, 910, 429]]<|/det|>\n<mark>[4]\n\n<|ref|>text<|/ref|><|det|>[[107, 446, 136, 466]]<|/det|>\n<label>(c)</label>\n\n<|ref|>text<|/ref|><|det|>[[149, 448, 373, 467]]<|/det|>\nradius of the circle is \\(15\\mathrm{cm}\\)\n\n<|ref|>text<|/ref|><|det|>[[702, 548, 860, 567]]<|/det|>\n<form>radius = ......... $ue$\n\n<|ref|>text<|/ref|><|det|>[[881, 548, 908, 566]]<|/det|>\n<mark>[6]\n\n<|ref|>text<|/ref|><|det|>[[77, 583, 96, 602]]<|/det|>\n<label>7</label>\n\n<|ref|>text<|/ref|><|det|>[[121, 580, 376, 602]]<|/det|>\nDefine radioactive half-life\n\n<|ref|>text<|/ref|><|det|>[[121, 604, 937, 661]]<|/det|>\nthe scale parallel to the scale perpendicular to the scale vertical to the scale in line with the bottom of the meniscus in line with the top of the meniscus in line with midway between the top and bottom of the meniscus\n\n<|ref|>text<|/ref|><|det|>[[697, 749, 863, 769]]<|/det|>\n<form>vertical = ....... $qt$\n\n<|ref|>text<|/ref|><|det|>[[887, 750, 920, 769]]<|/det|>\n<mark>[6]\n\n<|ref|>text<|/ref|><|det|>[[84, 790, 99, 809]]<|/det|>\n<label>9</label>\n\n<|ref|>text<|/ref|><|det|>[[121, 791, 438, 809]]<|/det|>\nspeed just before hitting the floor is \\(3.0m / s\\)\n\n<|ref|>text<|/ref|><|det|>[[119, 809, 922, 844]]<|/det|>\nstudent wishes to measure the speed of sound in air. She plans to measure the time between making a sound and hearing the echo from a cliff\n\n<｜end▁of▁sentence｜>"
    },
    "25": {
        "page": 25,
        "raw_output": "<|ref|>text<|/ref|><|det|>[[107, 83, 139, 102]]<|/det|>\n<label>(b)</label>\n\n<|ref|>text<|/ref|><|det|>[[149, 84, 364, 102]]<|/det|>\ntravelled in first 6.0s = m\n\n<|ref|>text<|/ref|><|det|>[[695, 184, 861, 201]]<|/det|>\n<form>6.0s = ............... $dv$\n\n<|ref|>text<|/ref|><|det|>[[883, 183, 913, 202]]<|/det|>\n<mark>[5]\n\n<|ref|>text<|/ref|><|det|>[[109, 214, 136, 234]]<|/det|>\n<label>(c)</label>\n\n<|ref|>text<|/ref|><|det|>[[148, 215, 183, 234]]<|/det|>\n<label>(iii)</label>\n\n<|ref|>text<|/ref|><|det|>[[183, 215, 719, 234]]<|/det|>\nSuggest one factor that could increase the total stopping distance\n\n<|ref|>text<|/ref|><|det|>[[183, 231, 920, 267]]<|/det|>\nDraw the straight line of best fit and a worst acceptable straight line on your graph. Both lines should be clearly labelled.\n\n<|ref|>text<|/ref|><|det|>[[183, 271, 428, 288]]<|/det|>\nFind an expression for \\(\\mathrm{f}^{-1}(x)\\)\n\n<|ref|>text<|/ref|><|det|>[[885, 381, 912, 396]]<|/det|>\n<mark>[8]\n\n<|ref|>text<|/ref|><|det|>[[141, 418, 175, 435]]<|/det|>\n<label>(vi)</label>\n\n<|ref|>text<|/ref|><|det|>[[185, 416, 468, 435]]<|/det|>\nFind the area of the triangle \\(PQR\\)\n\n<|ref|>text<|/ref|><|det|>[[185, 435, 379, 454]]<|/det|>\nstatements are correct?\n\n<|ref|>image<|/ref|><|det|>[[442, 463, 667, 580]]<|/det|>\n\n\n<|ref|>text<|/ref|><|det|>[[609, 667, 845, 686]]<|/det|>\n<form>area Find = ................... $vq$\n\n<|ref|>text<|/ref|><|det|>[[865, 668, 905, 687]]<|/det|>\n<mark>[20]\n\n<|ref|>text<|/ref|><|det|>[[79, 704, 104, 721]]<|/det|>\n<label>24</label>\n\n<|ref|>text<|/ref|><|det|>[[119, 704, 468, 721]]<|/det|>\nfollowing apparatus is available to the students:\n\n<|ref|>text<|/ref|><|det|>[[119, 723, 408, 740]]<|/det|>\nsealed box contains a fixed mass of gas\n\n<|ref|>text<|/ref|><|det|>[[890, 821, 917, 838]]<|/det|>\n<mark>[8]\n\n<|ref|>text<|/ref|><|det|>[[79, 852, 104, 872]]<|/det|>\n<label>10</label>\n\n<|ref|>text<|/ref|><|det|>[[114, 852, 146, 871]]<|/det|>\n<label>(d)</label>\n\n<|ref|>text<|/ref|><|det|>[[158, 852, 371, 871]]<|/det|>\nthe exact value of \\(f'(\\frac{2}{3}\\pi)\\).\n\n<｜end▁of▁sentence｜>"
    },
    "26": {
        "page": 26,
        "raw_output": "<|ref|>text<|/ref|><|det|>[[144, 83, 180, 101]]<|/det|>\n<label>(iii)</label>\n\n<|ref|>text<|/ref|><|det|>[[185, 84, 653, 103]]<|/det|>\nto this question by accurate drawing will not be accepted\n\n<|ref|>image<|/ref|><|det|>[[186, 112, 928, 431]]<|/det|>\n\n\n<|ref|>text<|/ref|><|det|>[[185, 434, 529, 452]]<|/det|>\nthe acceleration at the instant when \\(t = 6\\)\n\n<|ref|>text<|/ref|><|det|>[[863, 520, 903, 539]]<|/det|>\n<mark>[10]\n\n<|ref|>text<|/ref|><|det|>[[143, 554, 181, 573]]<|/det|>\n<label>(vi)</label>\n\n<|ref|>text<|/ref|><|det|>[[185, 554, 658, 572]]<|/det|>\nThe reflected wavefronts seem to come from a single point\n\n<|ref|>text<|/ref|><|det|>[[700, 658, 856, 676]]<|/det|>\n<form>from = ............ $ib$\n\n<|ref|>text<|/ref|><|det|>[[876, 657, 905, 676]]<|/det|>\n<mark>[4]\n\n<|ref|>text<|/ref|><|det|>[[141, 695, 166, 715]]<|/det|>\n<label>(i)</label>\n\n<|ref|>text<|/ref|><|det|>[[183, 695, 927, 730]]<|/det|>\npositively charged oil droplet falls in air in a uniform electric field that is vertically upwards. The droplet has a constant terminal speed \\(v_0\\) and the electric field strength is \\(E\\)\n\n<|ref|>text<|/ref|><|det|>[[876, 817, 905, 836]]<|/det|>\n<mark>[3]\n\n<|ref|>text<|/ref|><|det|>[[107, 853, 139, 871]]<|/det|>\n<label>(b)</label>\n\n<|ref|>text<|/ref|><|det|>[[151, 854, 920, 904]]<|/det|>\nSunday, teams of runners took part in a charity event. The time taken, in seconds, to run \\(50\\mathrm{m}\\) was recorded, correct to 1 decimal place, for each runner. The times recorded for 11 runners from each of the Gulls and the Herons are shown in the table\n\n<｜end▁of▁sentence｜>"
    },
    "27": {
        "page": 27,
        "raw_output": "<|ref|>text<|/ref|><|det|>[[143, 83, 173, 103]]<|/det|>\n<label>(ii)</label>\n\n<|ref|>text<|/ref|><|det|>[[185, 84, 391, 103]]<|/det|>\nthe effective resistance of\n\n<|ref|>text<|/ref|><|det|>[[715, 167, 860, 186]]<|/det|>\n<form>effective = .... $pz$\n\n<|ref|>text<|/ref|><|det|>[[881, 168, 910, 186]]<|/det|>\n<mark>[5]\n\n<|ref|>text<|/ref|><|det|>[[146, 204, 173, 222]]<|/det|>\n<label>(i)</label>\n\n<|ref|>text<|/ref|><|det|>[[183, 204, 411, 222]]<|/det|>\nyears old Beatrice years old\n\n<|ref|>text<|/ref|><|det|>[[880, 304, 910, 324]]<|/det|>\n<mark>[4]\n\n<|ref|>text<|/ref|><|det|>[[76, 339, 101, 357]]<|/det|>\n<label>18</label>\n\n<|ref|>text<|/ref|><|det|>[[118, 339, 324, 357]]<|/det|>\nShow that \\(\\mathrm{Var}(X) = \\frac{1}{12} a^2\\)\n\n<|ref|>text<|/ref|><|det|>[[121, 355, 447, 373]]<|/det|>\nwhich pair are both materials magnetic?\n\n<|ref|>text<|/ref|><|det|>[[109, 383, 141, 402]]<|/det|>\n<label>(b)</label>\n\n<|ref|>table<|/ref|><|det|>[[351, 403, 764, 514]]<|/det|>\n<table><tr><td></td><td>polarity of magnet 1</td><td>polarity of magnet 2</td></tr><tr><td>A</td><td>X is an N pole</td><td>Z is an N pole</td></tr><tr><td>B</td><td>X is an N pole</td><td>Z is an S pole</td></tr><tr><td>C</td><td>X is an S pole</td><td>Z is an N pole</td></tr><tr><td>D</td><td>X is an S pole</td><td>Z is an S pole</td></tr></table>\n\n<|ref|>text<|/ref|><|det|>[[151, 513, 484, 532]]<|/det|>\nproperty of the sound wave is increased?\n\n<|ref|>text<|/ref|><|det|>[[873, 619, 912, 638]]<|/det|>\n<mark>[10]\n\n<|ref|>text<|/ref|><|det|>[[109, 657, 139, 676]]<|/det|>\n<label>(a)</label>\n\n<|ref|>text<|/ref|><|det|>[[148, 656, 173, 676]]<|/det|>\n<label>(i)</label>\n\n<|ref|>text<|/ref|><|det|>[[183, 656, 507, 675]]<|/det|>\nFind the mean and standard deviation.\n\n<|ref|>text<|/ref|><|det|>[[185, 675, 463, 696]]<|/det|>\nCompare the charges of Q and R.\n\n<|ref|>text<|/ref|><|det|>[[645, 788, 855, 807]]<|/det|>\n<form>Compare Find = ....... $jj$\n\n<|ref|>text<|/ref|><|det|>[[876, 789, 905, 808]]<|/det|>\n<mark>[6]\n\n<｜end▁of▁sentence｜>"
    },
    "28": {
        "page": 28,
        "raw_output": "<|ref|>text<|/ref|><|det|>[[141, 85, 173, 103]]<|/det|>\n<label>(ii)</label>\n\n<|ref|>image<|/ref|><|det|>[[383, 107, 727, 324]]<|/det|>\n\n\n<|ref|>text<|/ref|><|det|>[[185, 330, 709, 349]]<|/det|>\nfully the single transformation that maps shape \\(A\\) onto shape \\(B\\)\n\n<|ref|>text<|/ref|><|det|>[[185, 351, 426, 370]]<|/det|>\ndoes the symbol \\(n\\) represent?\n\n<|ref|>text<|/ref|><|det|>[[703, 445, 858, 464]]<|/det|>\n<form>single = ......... $cm$\n\n<|ref|>text<|/ref|><|det|>[[880, 445, 908, 464]]<|/det|>\n<mark>[6]\n\n<｜end▁of▁sentence｜>"
    }
}